LICENSE.txt
README.rst
tbk/__init__.py
tbk/commerce.py
tbk/environments.py
tbk/services.py
tbk/soap/__init__.py
tbk/soap/exceptions.py
tbk/soap/requestor.py
tbk/soap/soap_client.py
tbk/soap/utils.py
tbk/soap/wsse.py
tbk/soap/zeep_client.py
python_tbk-0.2.2.dist-info/LICENSE.txt
python_tbk-0.2.2.dist-info/WHEEL
python_tbk-0.2.2.dist-info/METADATA
python_tbk-0.2.2.dist-info/RECORD
