Metadata-Version: 2.1
Name: python-tbk
Version: 0.2.2
Summary: Unofficial TBK Web Services Python SDK
Home-page: https://github.com/cornershop/python-tbk
License: MIT
Keywords: payments,python,transbank,chile
Author: Cornershop
Author-email: tech@cornershopapp.com
Requires-Python: >=2.7, !=3.0.*, !=3.1.*, !=3.2.*, !=3.3.*, !=3.4.*, !=3.5.*
Classifier: License :: OSI Approved :: MIT License
Classifier: Programming Language :: Python :: 2
Classifier: Programming Language :: Python :: 2.7
Classifier: Programming Language :: Python :: 3
Classifier: Programming Language :: Python :: 3.6
Classifier: Programming Language :: Python :: 3.7
Requires-Dist: typing (>=3.6); python_version >= "2.7" and python_version < "2.8"
Requires-Dist: xmlsec (>=0.6.1)
Requires-Dist: zeep (>=3.0.0)
Project-URL: Repository, https://github.com/cornershop/python-tbk
